{
  "compatibilityLevel": "JAVA_8",
  "minVersion": "0.7",
  "package": "org.polyfrost.vanillahud.mixin",
  "refmap": "mixins.vanillahud.refmap.json",
  "verbose": true,
  "client": [
    "appleskin.HUDOverlayHandlerMixin",
    "minecraft.ActionBarRecordEvent_GuiIngame_Mixin",
    "minecraft.Armor_GuiIngame_Mixin",
    "minecraft.BossStatusCallback_Mixin",
    "minecraft.EntityRendererMixin",
    "minecraft.Gui_CancelRect_Mixin",
    "minecraft.GuiIngameForgeMixin",
    "minecraft.GuiIngameForgeMixin_Cancel",
    "minecraft.GuiIngameMixin",
    "minecraft.GuiPlayerTabOverlayMixin",
    "minecraft.GuiSpectatorMixin",
    "minecraft.Health_GuiIngame_Mixin",
    "minecraft.Hunger_GuiIngame_Mixin",
    "minecraft.MountHealth_GuiIngame_Mixin",
    "minecraft.Oxygen_GuiIngame_Mixin",
    "minecraft.interfaces.GuiIngameAccessor",
    "minecraft.interfaces.GuiIngameForgeAccessor",
    "minecraft.interfaces.GuiPlayerTabOverlayAccessor",
    "minecraft.interfaces.GuiSpectatorAccessor",
    "minecraft.interfaces.MinecraftAccessor",
    "minecraft.interfaces.ZLevelAccessor_Mixin",
    "skyblock.RenderListenerMixin",
    "skyblock.TabListRendererMixin_SBA",
    "skyblock.TabListRendererMixin_SkyHanni"
  ]
}